Workbook

Sheet Assumptions
A1: Retention Business Case - Assumptions
A2: Blue = editable input. Yellow = key ASSUMPTION (not observed in the dataset). Currency is not stated in the dataset, so money is shown in currency units (CU).
A4: Gross margin on revenue | B4: 0.4 | C4: ASSUMPTION - dataset has no cost or margin data. Replace with a company figure if available.
A5: Annual discount rate | B5: 0.1 | C5: ASSUMPTION - used to discount future margin in CLV.
A6: CLV horizon (years) | B6: 5 | C6: ASSUMPTION - caps lifetime to avoid over-valuing very loyal segments.
A7: Retention cost per targeted customer (CU) | B7: 30 | C7: ASSUMPTION - outreach plus incentive cost per customer contacted. Test in Sensitivity sheet.
A8: Months per year | B8: 12 | C8: Constant used to annualise monthly charges.
A9: Minimum segment size to act on (customers) | B9: 100 | C9: Rule: smaller segments are too small to draw conclusions.
A10: Priority 1 threshold: share of total revenue at risk | B10: 0.1 | C10: Rule: segment must also churn above the overall rate.
A11: Churn period assumption | B11: Observed churn proportion is treated as an ANNUAL churn probability (ASSUMPTION). The dataset flag means 'left within the last month', but a 26.5% monthly rate would imply an average life of under 4 months, which contradicts the observed average tenure of 32.4 months.
A13: Scenario | B13: Assumed save rate
A14: Conservative | B14: 0.1 | C14: ASSUMPTION - share of would-be churners the programme retains. Not observed in the data.
A15: Base | B15: 0.2
A16: Optimistic | B16: 0.3

Sheet Segments
A1: Customer segments: Contract x Tenure band
A2: Blue columns B, C, F come from the SQL output in 04_customer_segmentation.sql. All other columns are formulas. Column M (1/0) chooses which segments the scenario targets.
A4: Segment | B4: Customers | C4: Churned | D4: Active customers | E4: Churn rate | F4: Active monthly revenue (CU) | G4: Avg monthly charge, active (CU) | H4: Est. annual revenue at risk (CU) - ESTIMATED | I4: Share of total risk | J4: Annual gross margin per active customer (CU) | K4: CLV per active customer, 5-yr (CU) - ESTIMATED | L4: Break-even save rate | M4: Target? (1/0) | N4: Priority
A5: Month-to-month / 1) 0-12 months | B5: 1994 | C5: 1024 | D5: =B5-C5 -> 970 | E5: =IF(B5=0,0,C5/B5) -> 0.51354062 | F5: 47785.05 | G5: =IF(D5=0,0,F5/D5) -> 49.262938 | H5: =F5*E5*Assumptions!$B$8 -> 294474.77 | I5: =IF($H$17=0,0,H5/$H$17) -> 0.37119169 | J5: =G5*Assumptions!$B$8*Assumptions!$B$4 -> 236.4621 | K5: =IF(D5=0,0,J5/(1+Assumptions!$B$5)*(1-((1-E5)/(1+Assumptions!$B$5))^Assumptions!$B$6)/(1-((1-E5)/(1+Assumptions!$B$5)))) -> 378.88668 | L5: =IF(E5*J5=0,"n/a",Assumptions!$B$7/(E5*J5)) -> 0.24705003 | M5: 1 | N5: =IF(B5<Assumptions!$B$9,"Too small to act on",IF(AND(E5>$E$17,I5>=Assumptions!$B$10),"Priority 1",IF(E5>$E$17,"Priority 2","Monitor"))) -> Priority 1
A6: Month-to-month / 2) 13-24 months | B6: 737 | C6: 278 | D6: =B6-C6 -> 459 | E6: =IF(B6=0,0,C6/B6) -> 0.37720488 | F6: 29100.85 | G6: =IF(D6=0,0,F6/D6) -> 63.400545 | H6: =F6*E6*Assumptions!$B$8 -> 131723.79 | I6: =IF($H$17=0,0,H6/$H$17) -> 0.16604063 | J6: =G6*Assumptions!$B$8*Assumptions!$B$4 -> 304.32261 | K6: =IF(D6=0,0,J6/(1+Assumptions!$B$5)*(1-((1-E6)/(1+Assumptions!$B$5))^Assumptions!$B$6)/(1-((1-E6)/(1+Assumptions!$B$5)))) -> 600.61745 | L6: =IF(E6*J6=0,"n/a",Assumptions!$B$7/(E6*J6)) -> 0.26134231 | M6: 1 | N6: =IF(B6<Assumptions!$B$9,"Too small to act on",IF(AND(E6>$E$17,I6>=Assumptions!$B$10),"Priority 1",IF(E6>$E$17,"Priority 2","Monitor"))) -> Priority 1
A7: Month-to-month / 3) 25-48 months | B7: 802 | C7: 264 | D7: =B7-C7 -> 538 | E7: =IF(B7=0,0,C7/B7) -> 0.32917706 | F7: 38347.05 | G7: =IF(D7=0,0,F7/D7) -> 71.277045 | H7: =F7*E7*Assumptions!$B$8 -> 151475.63 | I7: =IF($H$17=0,0,H7/$H$17) -> 0.19093824 | J7: =G7*Assumptions!$B$8*Assumptions!$B$4 -> 342.12981 | K7: =IF(D7=0,0,J7/(1+Assumptions!$B$5)*(1-((1-E7)/(1+Assumptions!$B$5))^Assumptions!$B$6)/(1-((1-E7)/(1+Assumptions!$B$5)))) -> 729.93594 | L7: =IF(E7*J7=0,"n/a",Assumptions!$B$7/(E7*J7)) -> 0.26637948 | M7: 1 | N7: =IF(B7<Assumptions!$B$9,"Too small to act on",IF(AND(E7>$E$17,I7>=Assumptions!$B$10),"Priority 1",IF(E7>$E$17,"Priority 2","Monitor"))) -> Priority 1
A8: Month-to-month / 4) 49+ months | B8: 342 | C8: 89 | D8: =B8-C8 -> 253 | E8: =IF(B8=0,0,C8/B8) -> 0.26023392 | F8: 21214.1 | G8: =IF(D8=0,0,F8/D8) -> 83.850198 | H8: =F8*E8*Assumptions!$B$8 -> 66247.54 | I8: =IF($H$17=0,0,H8/$H$17) -> 0.083506429 | J8: =G8*Assumptions!$B$8*Assumptions!$B$4 -> 402.48095 | K8: =IF(D8=0,0,J8/(1+Assumptions!$B$5)*(1-((1-E8)/(1+Assumptions!$B$5))^Assumptions!$B$6)/(1-((1-E8)/(1+Assumptions!$B$5)))) -> 963.57825 | L8: =IF(E8*J8=0,"n/a",Assumptions!$B$7/(E8*J8)) -> 0.28642573 | M8: 0 | N8: =IF(B8<Assumptions!$B$9,"Too small to act on",IF(AND(E8>$E$17,I8>=Assumptions!$B$10),"Priority 1",IF(E8>$E$17,"Priority 2","Monitor"))) -> Monitor
A9: One year / 1) 0-12 months | B9: 124 | C9: 13 | D9: =B9-C9 -> 111 | E9: =IF(B9=0,0,C9/B9) -> 0.10483871 | F9: 3786.1 | G9: =IF(D9=0,0,F9/D9) -> 34.109009 | H9: =F9*E9*Assumptions!$B$8 -> 4763.1581 | I9: =IF($H$17=0,0,H9/$H$17) -> 0.0060040617 | J9: =G9*Assumptions!$B$8*Assumptions!$B$4 -> 163.72324 | K9: =IF(D9=0,0,J9/(1+Assumptions!$B$5)*(1-((1-E9)/(1+Assumptions!$B$5))^Assumptions!$B$6)/(1-((1-E9)/(1+Assumptions!$B$5)))) -> 514.01852 | L9: =IF(E9*J9=0,"n/a",Assumptions!$B$7/(E9*J9)) -> 1.74779 | M9: 0 | N9: =IF(B9<Assumptions!$B$9,"Too small to act on",IF(AND(E9>$E$17,I9>=Assumptions!$B$10),"Priority 1",IF(E9>$E$17,"Priority 2","Monitor"))) -> Monitor
A10: One year / 2) 13-24 months | B10: 197 | C10: 16 | D10: =B10-C10 -> 181 | E10: =IF(B10=0,0,C10/B10) -> 0.081218274 | F10: 7739.75 | G10: =IF(D10=0,0,F10/D10) -> 42.76105 | H10: =F10*E10*Assumptions!$B$8 -> 7543.3096 | I10: =IF($H$17=0,0,H10/$H$17) -> 0.0095085018 | J10: =G10*Assumptions!$B$8*Assumptions!$B$4 -> 205.25304 | K10: =IF(D10=0,0,J10/(1+Assumptions!$B$5)*(1-((1-E10)/(1+Assumptions!$B$5))^Assumptions!$B$6)/(1-((1-E10)/(1+Assumptions!$B$5)))) -> 672.17516 | L10: =IF(E10*J10=0,"n/a",Assumptions!$B$7/(E10*J10)) -> 1.7996079 | M10: 0 | N10: =IF(B10<Assumptions!$B$9,"Too small to act on",IF(AND(E10>$E$17,I10>=Assumptions!$B$10),"Priority 1",IF(E10>$E$17,"Priority 2","Monitor"))) -> Monitor
A11: One year / 3) 25-48 months | B11: 518 | C11: 55 | D11: =B11-C11 -> 463 | E11: =IF(B11=0,0,C11/B11) -> 0.10617761 | F11: 27571.95 | G11: =IF(D11=0,0,F11/D11) -> 59.550648 | H11: =F11*E11*Assumptions!$B$8 -> 35130.284 | I11: =IF($H$17=0,0,H11/$H$17) -> 0.044282468 | J11: =G11*Assumptions!$B$8*Assumptions!$B$4 -> 285.84311 | K11: =IF(D11=0,0,J11/(1+Assumptions!$B$5)*(1-((1-E11)/(1+Assumptions!$B$5))^Assumptions!$B$6)/(1-((1-E11)/(1+Assumptions!$B$5)))) -> 895.2824 | L11: =IF(E11*J11=0,"n/a",Assumptions!$B$7/(E11*J11)) -> 0.98846341 | M11: 0 | N11: =IF(B11<Assumptions!$B$9,"Too small to act on",IF(AND(E11>$E$17,I11>=Assumptions!$B$10),"Priority 1",IF(E11>$E$17,"Priority 2","Monitor"))) -> Monitor
A12: One year / 4) 49+ months | B12: 634 | C12: 82 | D12: =B12-C12 -> 552 | E12: =IF(B12=0,0,C12/B12) -> 0.12933754 | F12: 42600.35 | G12: =IF(D12=0,0,F12/D12) -> 77.174547 | H12: =F12*E12*Assumptions!$B$8 -> 66117.893 | I12: =IF($H$17=0,0,H12/$H$17) -> 0.083343007 | J12: =G12*Assumptions!$B$8*Assumptions!$B$4 -> 370.43783 | K12: =IF(D12=0,0,J12/(1+Assumptions!$B$5)*(1-((1-E12)/(1+Assumptions!$B$5))^Assumptions!$B$6)/(1-((1-E12)/(1+Assumptions!$B$5)))) -> 1113.4571 | L12: =IF(E12*J12=0,"n/a",Assumptions!$B$7/(E12*J12)) -> 0.62615425 | M12: 0 | N12: =IF(B12<Assumptions!$B$9,"Too small to act on",IF(AND(E12>$E$17,I12>=Assumptions!$B$10),"Priority 1",IF(E12>$E$17,"Priority 2","Monitor"))) -> Monitor
A13: Two year / 1) 0-12 months | B13: 68 | C13: 0 | D13: =B13-C13 -> 68 | E13: =IF(B13=0,0,C13/B13) -> 0 | F13: 2104.35 | G13: =IF(D13=0,0,F13/D13) -> 30.946324 | H13: =F13*E13*Assumptions!$B$8 -> 0 | I13: =IF($H$17=0,0,H13/$H$17) -> 0 | J13: =G13*Assumptions!$B$8*Assumptions!$B$4 -> 148.54235 | K13: =IF(D13=0,0,J13/(1+Assumptions!$B$5)*(1-((1-E13)/(1+Assumptions!$B$5))^Assumptions!$B$6)/(1-((1-E13)/(1+Assumptions!$B$5)))) -> 563.09239 | L13: =IF(E13*J13=0,"n/a",Assumptions!$B$7/(E13*J13)) -> n/a | M13: 0 | N13: =IF(B13<Assumptions!$B$9,"Too small to act on",IF(AND(E13>$E$17,I13>=Assumptions!$B$10),"Priority 1",IF(E13>$E$17,"Priority 2","Monitor"))) -> Too small to act on
A14: Two year / 2) 13-24 months | B14: 90 | C14: 0 | D14: =B14-C14 -> 90 | E14: =IF(B14=0,0,C14/B14) -> 0 | F14: 2907.6 | G14: =IF(D14=0,0,F14/D14) -> 32.306667 | H14: =F14*E14*Assumptions!$B$8 -> 0 | I14: =IF($H$17=0,0,H14/$H$17) -> 0 | J14: =G14*Assumptions!$B$8*Assumptions!$B$4 -> 155.072 | K14: =IF(D14=0,0,J14/(1+Assumptions!$B$5)*(1-((1-E14)/(1+Assumptions!$B$5))^Assumptions!$B$6)/(1-((1-E14)/(1+Assumptions!$B$5)))) -> 587.84489 | L14: =IF(E14*J14=0,"n/a",Assumptions!$B$7/(E14*J14)) -> n/a | M14: 0 | N14: =IF(B14<Assumptions!$B$9,"Too small to act on",IF(AND(E14>$E$17,I14>=Assumptions!$B$10),"Priority 1",IF(E14>$E$17,"Priority 2","Monitor"))) -> Too small to act on
A15: Two year / 3) 25-48 months | B15: 274 | C15: 6 | D15: =B15-C15 -> 268 | E15: =IF(B15=0,0,C15/B15) -> 0.02189781 | F15: 11711.8 | G15: =IF(D15=0,0,F15/D15) -> 43.700746 | H15: =F15*E15*Assumptions!$B$8 -> 3077.5533 | I15: =IF($H$17=0,0,H15/$H$17) -> 0.0038793212 | J15: =G15*Assumptions!$B$8*Assumptions!$B$4 -> 209.76358 | K15: =IF(D15=0,0,J15/(1+Assumptions!$B$5)*(1-((1-E15)/(1+Assumptions!$B$5))^Assumptions!$B$6)/(1-((1-E15)/(1+Assumptions!$B$5)))) -> 764.29972 | L15: =IF(E15*J15=0,"n/a",Assumptions!$B$7/(E15*J15)) -> 6.5311623 | M15: 0 | N15: =IF(B15<Assumptions!$B$9,"Too small to act on",IF(AND(E15>$E$17,I15>=Assumptions!$B$10),"Priority 1",IF(E15>$E$17,"Priority 2","Monitor"))) -> Monitor
A16: Two year / 4) 49+ months | B16: 1263 | C16: 42 | D16: =B16-C16 -> 1221 | E16: =IF(B16=0,0,C16/B16) -> 0.033254157 | F16: 82116.8 | G16: =IF(D16=0,0,F16/D16) -> 67.253726 | H16: =F16*E16*Assumptions!$B$8 -> 32768.699 | I16: =IF($H$17=0,0,H16/$H$17) -> 0.04130564 | J16: =G16*Assumptions!$B$8*Assumptions!$B$4 -> 322.81789 | K16: =IF(D16=0,0,J16/(1+Assumptions!$B$5)*(1-((1-E16)/(1+Assumptions!$B$5))^Assumptions!$B$6)/(1-((1-E16)/(1+Assumptions!$B$5)))) -> 1152.3644 | L16: =IF(E16*J16=0,"n/a",Assumptions!$B$7/(E16*J16)) -> 2.7945876 | M16: 0 | N16: =IF(B16<Assumptions!$B$9,"Too small to act on",IF(AND(E16>$E$17,I16>=Assumptions!$B$10),"Priority 1",IF(E16>$E$17,"Priority 2","Monitor"))) -> Monitor
A17: Total / overall | B17: =SUM(B5:B16) -> 7043 | C17: =SUM(C5:C16) -> 1869 | D17: =SUM(D5:D16) -> 5174 | E17: =C17/B17 -> 0.26536987 | F17: =SUM(F5:F16) -> 316985.75 | H17: =SUM(H5:H16) -> 793322.63 | I17: =SUM(I5:I16) -> 1
A19: Notes
A20: Est. annual revenue at risk = active monthly revenue x segment churn rate x 12. ESTIMATED: assumes the observed churn rate repeats over the next year (ASSUMPTION).
A21: CLV per active customer = sum over the horizon of [annual gross margin x (1 - churn rate)^(t-1) / (1 + discount)^t]. ESTIMATED, uses ASSUMPTIONS on the Assumptions sheet.
A22: Break-even save rate = retention cost per target / (churn rate x annual gross margin per active customer). Above this save rate the 12-month gross margin preserved exceeds the cost.
A23: Tenure band for churned customers is tenure at departure; for active customers it is tenure to date.

Sheet Scenarios
A1: Retention budget scenarios (targets = segments flagged 1 on the Segments sheet)
A3: Metric | B3: Conservative | C3: Base | D3: Optimistic
A4: Assumed save rate | B4: =Assumptions!$B$14 -> 0.1 | C4: =Assumptions!$B$15 -> 0.2 | D4: =Assumptions!$B$16 -> 0.3
A5: Target customers (active, in flagged segments) | B5: =SUMPRODUCT(Segments!$M$5:$M$16,Segments!$D$5:$D$16) -> 1967 | C5: =SUMPRODUCT(Segments!$M$5:$M$16,Segments!$D$5:$D$16) -> 1967 | D5: =SUMPRODUCT(Segments!$M$5:$M$16,Segments!$D$5:$D$16) -> 1967
A6: Expected churners among targets without a programme (ESTIMATED) | B6: =SUMPRODUCT(Segments!$M$5:$M$16,Segments!$D$5:$D$16,Segments!$E$5:$E$16) -> 848.3687 | C6: =SUMPRODUCT(Segments!$M$5:$M$16,Segments!$D$5:$D$16,Segments!$E$5:$E$16) -> 848.3687 | D6: =SUMPRODUCT(Segments!$M$5:$M$16,Segments!$D$5:$D$16,Segments!$E$5:$E$16) -> 848.3687
A7: Customers retained (ESTIMATED) | B7: =B6*B4 -> 84.83687 | C7: =C6*C4 -> 169.67374 | D7: =D6*D4 -> 254.51061
A8: Annual revenue preserved (CU, ESTIMATED) | B8: =SUMPRODUCT(Segments!$M$5:$M$16,Segments!$D$5:$D$16,Segments!$E$5:$E$16,Segments!$G$5:$G$16)*Assumptions!$B$8*B4 -> 57767.419 | C8: =SUMPRODUCT(Segments!$M$5:$M$16,Segments!$D$5:$D$16,Segments!$E$5:$E$16,Segments!$G$5:$G$16)*Assumptions!$B$8*C4 -> 115534.84 | D8: =SUMPRODUCT(Segments!$M$5:$M$16,Segments!$D$5:$D$16,Segments!$E$5:$E$16,Segments!$G$5:$G$16)*Assumptions!$B$8*D4 -> 173302.26
A9: Gross margin preserved, 12 months (CU, ESTIMATED) | B9: =B8*Assumptions!$B$4 -> 23106.968 | C9: =C8*Assumptions!$B$4 -> 46213.935 | D9: =D8*Assumptions!$B$4 -> 69320.903
A10: Retention cost (CU, ASSUMPTION-based) | B10: =B5*Assumptions!$B$7 -> 59010 | C10: =C5*Assumptions!$B$7 -> 59010 | D10: =D5*Assumptions!$B$7 -> 59010
A11: Net benefit, 12-month basis (CU, ESTIMATED) | B11: =B9-B10 -> -35903.032 | C11: =C9-C10 -> -12796.065 | D11: =D9-D10 -> 10310.903
A12: ROI, 12-month basis (ESTIMATED) | B12: =IF(B10=0,0,B11/B10) -> -0.60842285 | C12: =IF(C10=0,0,C11/C10) -> -0.2168457 | D12: =IF(D10=0,0,D11/D10) -> 0.17473146
A13: CLV preserved, 5-year basis (CU, ESTIMATED) | B13: =SUMPRODUCT(Segments!$M$5:$M$16,Segments!$D$5:$D$16,Segments!$E$5:$E$16,Segments!$K$5:$K$16)*B4 -> 42199.527 | C13: =SUMPRODUCT(Segments!$M$5:$M$16,Segments!$D$5:$D$16,Segments!$E$5:$E$16,Segments!$K$5:$K$16)*C4 -> 84399.054 | D13: =SUMPRODUCT(Segments!$M$5:$M$16,Segments!$D$5:$D$16,Segments!$E$5:$E$16,Segments!$K$5:$K$16)*D4 -> 126598.58
A14: Net benefit, CLV basis (CU, ESTIMATED) | B14: =B13-B10 -> -16810.473 | C14: =C13-C10 -> 25389.054 | D14: =D13-D10 -> 67588.582
A15: ROI, CLV basis (ESTIMATED) | B15: =IF(B10=0,0,B14/B10) -> -0.28487498 | C15: =IF(C10=0,0,C14/C10) -> 0.43025003 | D15: =IF(D10=0,0,D14/D10) -> 1.1453751
A17: 12-month basis counts one year of gross margin per saved customer (conservative). CLV basis counts the discounted margin over the horizon.

Sheet Sensitivity
A1: Sensitivity: 12-month ROI vs save rate and cost per targeted customer
A3: Target customers | B3: =Scenarios!B5 -> 1967
A4: Gross margin preserved at 100% save, 12 months (CU) | B4: =SUMPRODUCT(Segments!$M$5:$M$16,Segments!$D$5:$D$16,Segments!$E$5:$E$16,Segments!$G$5:$G$16)*Assumptions!$B$8*Assumptions!$B$4 -> 231069.68
A6: Save rate \ cost per target (CU) | B6: 15 | C6: 30 | D6: 45 | E6: 60
A7: 0.05 | B7: =($A7*$B$4-$B$3*B$6)/($B$3*B$6) -> -0.60842285 | C7: =($A7*$B$4-$B$3*C$6)/($B$3*C$6) -> -0.80421142 | D7: =($A7*$B$4-$B$3*D$6)/($B$3*D$6) -> -0.86947428 | E7: =($A7*$B$4-$B$3*E$6)/($B$3*E$6) -> -0.90210571
A8: 0.1 | B8: =($A8*$B$4-$B$3*B$6)/($B$3*B$6) -> -0.2168457 | C8: =($A8*$B$4-$B$3*C$6)/($B$3*C$6) -> -0.60842285 | D8: =($A8*$B$4-$B$3*D$6)/($B$3*D$6) -> -0.73894857 | E8: =($A8*$B$4-$B$3*E$6)/($B$3*E$6) -> -0.80421142
A9: 0.15 | B9: =($A9*$B$4-$B$3*B$6)/($B$3*B$6) -> 0.17473146 | C9: =($A9*$B$4-$B$3*C$6)/($B$3*C$6) -> -0.41263427 | D9: =($A9*$B$4-$B$3*D$6)/($B$3*D$6) -> -0.60842285 | E9: =($A9*$B$4-$B$3*E$6)/($B$3*E$6) -> -0.70631714
A10: 0.2 | B10: =($A10*$B$4-$B$3*B$6)/($B$3*B$6) -> 0.56630861 | C10: =($A10*$B$4-$B$3*C$6)/($B$3*C$6) -> -0.2168457 | D10: =($A10*$B$4-$B$3*D$6)/($B$3*D$6) -> -0.47789713 | E10: =($A10*$B$4-$B$3*E$6)/($B$3*E$6) -> -0.60842285
A11: 0.25 | B11: =($A11*$B$4-$B$3*B$6)/($B$3*B$6) -> 0.95788576 | C11: =($A11*$B$4-$B$3*C$6)/($B$3*C$6) -> -0.02105712 | D11: =($A11*$B$4-$B$3*D$6)/($B$3*D$6) -> -0.34737141 | E11: =($A11*$B$4-$B$3*E$6)/($B$3*E$6) -> -0.51052856
A12: 0.3 | B12: =($A12*$B$4-$B$3*B$6)/($B$3*B$6) -> 1.3494629 | C12: =($A12*$B$4-$B$3*C$6)/($B$3*C$6) -> 0.17473146 | D12: =($A12*$B$4-$B$3*D$6)/($B$3*D$6) -> -0.2168457 | E12: =($A12*$B$4-$B$3*E$6)/($B$3*E$6) -> -0.41263427
A13: 0.35 | B13: =($A13*$B$4-$B$3*B$6)/($B$3*B$6) -> 1.7410401 | C13: =($A13*$B$4-$B$3*C$6)/($B$3*C$6) -> 0.37052003 | D13: =($A13*$B$4-$B$3*D$6)/($B$3*D$6) -> -0.086319978 | E13: =($A13*$B$4-$B$3*E$6)/($B$3*E$6) -> -0.31473998
A14: 0.4 | B14: =($A14*$B$4-$B$3*B$6)/($B$3*B$6) -> 2.1326172 | C14: =($A14*$B$4-$B$3*C$6)/($B$3*C$6) -> 0.56630861 | D14: =($A14*$B$4-$B$3*D$6)/($B$3*D$6) -> 0.044205739 | E14: =($A14*$B$4-$B$3*E$6)/($B$3*E$6) -> -0.2168457
A16: Break-even save rate | B16: =$B$3*B6/$B$4 -> 0.12768876 | C16: =$B$3*C6/$B$4 -> 0.25537751 | D16: =$B$3*D6/$B$4 -> 0.38306627 | E16: =$B$3*E6/$B$4 -> 0.51075503

Sheet Focused
A1: Focused sub-segments inside month-to-month, 0-12 months (smaller, higher-churn targets)
A2: Sub-segments overlap each other, so do not add them together. The scenario below targets the first row only (fiber optic).
A4: Segment | B4: Customers | C4: Churned | D4: Active customers | E4: Churn rate | F4: Active monthly revenue (CU) | G4: Avg monthly charge, active (CU) | H4: Est. annual revenue at risk (CU) - ESTIMATED | I4: Share of total risk (all 12 segments) | J4: Annual gross margin per active customer (CU) | K4: CLV per active customer, 5-yr (CU) - ESTIMATED | L4: Break-even save rate
A5: M2M / 0-12 months / Fiber optic | B5: 916 | C5: 643 | D5: =B5-C5 -> 273 | E5: =IF(B5=0,0,C5/B5) -> 0.70196507 | F5: 22004.85 | G5: =IF(D5=0,0,F5/D5) -> 80.603846 | H5: =F5*E5*Assumptions!$B$8 -> 185359.63 | I5: =H5/Segments!$H$17 -> 0.23364975 | J5: =G5*Assumptions!$B$8*Assumptions!$B$4 -> 386.89846 | K5: =IF(D5=0,0,J5/(1+Assumptions!$B$5)*(1-((1-E5)/(1+Assumptions!$B$5))^Assumptions!$B$6)/(1-((1-E5)/(1+Assumptions!$B$5)))) -> 481.73366 | L5: =IF(E5*J5=0,"n/a",Assumptions!$B$7/(E5*J5)) -> 0.11046094
A6: M2M / 0-12 months / Electronic check | B6: 954 | C6: 602 | D6: =B6-C6 -> 352 | E6: =IF(B6=0,0,C6/B6) -> 0.63102725 | F6: 22368.4 | G6: =IF(D6=0,0,F6/D6) -> 63.546591 | H6: =F6*E6*Assumptions!$B$8 -> 169380.84 | I6: =H6/Segments!$H$17 -> 0.21350814 | J6: =G6*Assumptions!$B$8*Assumptions!$B$4 -> 305.02364 | K6: =IF(D6=0,0,J6/(1+Assumptions!$B$5)*(1-((1-E6)/(1+Assumptions!$B$5))^Assumptions!$B$6)/(1-((1-E6)/(1+Assumptions!$B$5)))) -> 415.48167 | L6: =IF(E6*J6=0,"n/a",Assumptions!$B$7/(E6*J6)) -> 0.15586178
A7: M2M / 0-12 months / Not fiber optic | B7: 1078 | C7: 381 | D7: =B7-C7 -> 697 | E7: =IF(B7=0,0,C7/B7) -> 0.35343228 | F7: 25780.2 | G7: =IF(D7=0,0,F7/D7) -> 36.987374 | H7: =F7*E7*Assumptions!$B$8 -> 109338.66 | I7: =H7/Segments!$H$17 -> 0.1378237 | J7: =G7*Assumptions!$B$8*Assumptions!$B$4 -> 177.5394 | K7: =IF(D7=0,0,J7/(1+Assumptions!$B$5)*(1-((1-E7)/(1+Assumptions!$B$5))^Assumptions!$B$6)/(1-((1-E7)/(1+Assumptions!$B$5)))) -> 364.07364 | L7: =IF(E7*J7=0,"n/a",Assumptions!$B$7/(E7*J7)) -> 0.47810171
A10: Scenario on the fiber optic sub-segment
A11: Metric | B11: Conservative | C11: Base | D11: Optimistic
A12: Assumed save rate | B12: =Assumptions!$B$14 -> 0.1 | C12: =Assumptions!$B$15 -> 0.2 | D12: =Assumptions!$B$16 -> 0.3
A13: Target customers | B13: =$D$5 -> 273 | C13: =$D$5 -> 273 | D13: =$D$5 -> 273
A14: Customers retained (ESTIMATED) | B14: =$D$5*$E$5*B12 -> 19.163646 | C14: =$D$5*$E$5*C12 -> 38.327293 | D14: =$D$5*$E$5*D12 -> 57.490939
A15: Gross margin preserved, 12 months (CU, ESTIMATED) | B15: =$D$5*$E$5*$G$5*Assumptions!$B$8*Assumptions!$B$4*B12 -> 7414.3853 | C15: =$D$5*$E$5*$G$5*Assumptions!$B$8*Assumptions!$B$4*C12 -> 14828.771 | D15: =$D$5*$E$5*$G$5*Assumptions!$B$8*Assumptions!$B$4*D12 -> 22243.156
A16: Retention cost (CU, ASSUMPTION-based) | B16: =$D$5*Assumptions!$B$7 -> 8190 | C16: =$D$5*Assumptions!$B$7 -> 8190 | D16: =$D$5*Assumptions!$B$7 -> 8190
A17: Net benefit, 12-month basis (CU, ESTIMATED) | B17: =B15-B16 -> -775.61473 | C17: =C15-C16 -> 6638.7705 | D17: =D15-D16 -> 14053.156
A18: ROI, 12-month basis (ESTIMATED) | B18: =IF(B16=0,0,B17/B16) -> -0.094702654 | C18: =IF(C16=0,0,C17/C16) -> 0.81059469 | D18: =IF(D16=0,0,D17/D16) -> 1.715892

Sheet Notes
A1: How to use this workbook
A3: 1. Change blue inputs on Assumptions (margin, discount rate, cost per target, save rates). Everything else recalculates.
A4: 2. Segments: columns B, C, F are SQL outputs (04_customer_segmentation.sql). Re-run the SQL if the data changes.
A5: 3. Scenarios: set column M on Segments to 1 for segments you want to target.
A6: 4. Labels: ASSUMPTION = not in the data. ESTIMATED = calculated using an assumption. Everything else is calculated directly from the dataset.
A7: 5. Currency is not stated in the dataset. Figures are in currency units (CU).
A8: 6. Association is not causation: segment churn rates describe what was observed, not what a programme will achieve.
